manify/__init__.py
manify/manifolds.py
manify-0.2.1.dist-info/licenses/LICENSE.md
manify-0.2.1.dist-info/METADATA
manify-0.2.1.dist-info/WHEEL
manify-0.2.1.dist-info/top_level.txt
manify-0.2.1.dist-info/RECORD
