Metadata-Version: 2.4
Name: manify
Version: 0.2.1
Summary: Manifold-based machine learning
Author-email: Philippe Chlenski <pac@cs.columbia.edu>, Kaizhu Du <kd2814@columbia.edu>
License-File: LICENSE.md
Requires-Dist: torch
Requires-Dist: geoopt>=0.5.1
Requires-Dist: numpy
Requires-Dist: tqdm
Requires-Dist: cvxpy
Requires-Dist: scikit-learn==1.5.1
Requires-Dist: datasets
Provides-Extra: dev
Requires-Dist: mypy; extra == "dev"
Requires-Dist: jaxtyping; extra == "dev"
Requires-Dist: beartype; extra == "dev"
Requires-Dist: pytest; extra == "dev"
Requires-Dist: pytest-cov; extra == "dev"
Requires-Dist: pytest-env; extra == "dev"
Requires-Dist: ruff; extra == "dev"
Requires-Dist: pre-commit; extra == "dev"
Requires-Dist: typing_extensions; extra == "dev"
Requires-Dist: pygments; extra == "dev"
Provides-Extra: docs
Requires-Dist: mkdocs; extra == "docs"
Requires-Dist: mkdocs-material; extra == "docs"
Requires-Dist: mkdocstrings[python]; extra == "docs"
Requires-Dist: mkdocs-autorefs; extra == "docs"
Requires-Dist: mkdocs-gen-files; extra == "docs"
Requires-Dist: griffe; extra == "docs"
Dynamic: license-file
